{
  "Country": "__",
  "Rating": 0,
  "Type": "U",
  "Code": "",
  "Title": "นั่งเทียนเบาะหลังรถ",
  "Actress": [],
  "Tag": [
    "clip"
  ],
  "Hash": "b88df16664306e06062e63fd34b7db61",
  "CreatedTime": "2015-02-16 21:56:37",
  "ModifiedTime": "2015-03-21 22:13:17",
  "ViewTime": "2015-03-08 00:32:06",
  "FilePath": [
    "Q:\\QH\\__+0!U()$นั่งเทียนเบาะหลังรถ${}[clip]=b88df16664306e06062e63fd34b7db61.mp4",
    "G:\\GXXX\\__+0!U()$นั่งเทียนเบาะหลังรถ${}[clip]=b88df16664306e06062e63fd34b7db61.mp4"
  ],
  "FileSize": 8600342,
  "Story": "",
  "CountPlay": "2"
}
