{
  "Country": "US",
  "Rating": 2,
  "Type": "X",
  "Code": "",
  "Title": "Jiggle Shanes World 42 cd1",
  "Actress": [],
  "Tag": [
    "boat",
    "mature",
    "party"
  ],
  "Hash": "b987abb4d55a99dacb5bf337259fa8e8",
  "CreatedTime": "2013-06-26 14:47:42",
  "ModifiedTime": "2013-06-26 14:48:36",
  "ViewTime": "2013-06-26 14:48:00",
  "FilePath": [
    "X:\\X5\\US+2!X()$Jiggle Shanes World 42 cd1${}[boat,mature,party]=b987abb4d55a99dacb5bf337259fa8e8.avi"
  ],
  "FileSize": 730296320,
  "Story": "",
  "CountPlay": "1"
}
