{
  "Country": "US",
  "Rating": 4,
  "Type": "X",
  "Code": "",
  "Title": "A Hot wife Blind folded",
  "Actress": [],
  "Tag": [
    "720p",
    "mature",
    "swing",
    "wife"
  ],
  "Hash": "bb46eb67ab3490a2622065881d995450",
  "CreatedTime": "2015-03-02 23:41:49",
  "ModifiedTime": "2022-01-13 18:41:43",
  "ViewTime": "2015-03-02 23:42:13",
  "FilePath": [
    "T:\\4X-300\\US+4!X()$A Hot wife Blind folded${}[720p,mature,swing,wife]=bb46eb67ab3490a2622065881d995450.mp4",
    "X:\\4X-300\\US+4!X()$A Hot wife Blind folded${}[720p,mature,swing,wife]=bb46eb67ab3490a2622065881d995450.mp4"
  ],
  "FileSize": 2675751999,
  "Story": "",
  "CountPlay": "1"
}
