{
  "Country": "JP",
  "Rating": 4,
  "Type": "C",
  "Code": "MDYD-918",
  "Title": "You have Felt Committed To The Best Friend Of Her Husband",
  "Actress": [
    "SAYURI SHIRAISHI"
  ],
  "Tag": [
    "lover",
    "mature",
    "rape",
    "wife"
  ],
  "Hash": "bdaee8f6b7d157b1aaf4f55d5bf9b3ad",
  "CreatedTime": "2015-02-19 00:02:51",
  "ModifiedTime": "2025-08-05 23:47:18",
  "ViewTime": "2015-04-06 20:12:36",
  "FilePath": [
    "T:\\4X-100\\JP+4!C(MDYD-918)$You have Felt Committed To The Best Friend Of Her Husband${SAYURI SHIRAISHI}[lover,mature,rape,wife]=bdaee8f6b7d157b1aaf4f55d5bf9b3ad.mp4",
    "X:\\4X-100\\JP+4!C(MDYD-918)$You have Felt Committed To The Best Friend Of Her Husband${SAYURI SHIRAISHI}[lover,mature,rape,wife]=bdaee8f6b7d157b1aaf4f55d5bf9b3ad.mp4"
  ],
  "FileSize": 1519895467,
  "Story": "",
  "CountPlay": "1"
}
