{
  "Country": "US",
  "Rating": 2,
  "Type": "X",
  "Code": "",
  "Title": "เยอรมัน - สาวใหญ่อึ๊บเด็กหนุ่ม",
  "Actress": [],
  "Tag": [
    "big-breast",
    "mature",
    "slut"
  ],
  "Hash": "44a1dbd05c0f0dc1c15439b54fb13e29",
  "CreatedTime": "2013-08-10 16:00:54",
  "ModifiedTime": "2013-08-11 13:10:53",
  "ViewTime": "2013-08-11 13:10:28",
  "FilePath": [
    "X:\\XB\\US+2!X()$เยอรมัน - สาวใหญ่อึ๊บเด็กหนุ่ม${}[big-breast,mature,slut]=44a1dbd05c0f0dc1c15439b54fb13e29.avi"
  ],
  "FileSize": 1382967296,
  "Story": "",
  "CountPlay": "1"
}
