{
  "Country": "JP",
  "Rating": 4,
  "Type": "C",
  "Code": "DANDY-185",
  "Title": "Horny Housewives 4",
  "Actress": [],
  "Tag": [
    "housewife",
    "lover",
    "mature",
    "slut"
  ],
  "Hash": "4db0c82c0db638faec1cabef80c03113",
  "CreatedTime": "2013-07-27 22:51:49",
  "ModifiedTime": "2013-07-27 22:56:48",
  "ViewTime": "2013-07-27 22:54:20",
  "FilePath": [
    "X:\\X7\\JP+4!C(DANDY-185)$Horny Housewives 4${}[housewife,lover,mature,slut]=4db0c82c0db638faec1cabef80c03113.avi"
  ],
  "FileSize": 1813985378,
  "Story": "แม่บ้านอารมณ์เปลี่ยวให้ท่าช่างที่มาซ่อมบ้าน",
  "CountPlay": "1"
}
