{
  "Country": "US",
  "Rating": 4,
  "Type": "X",
  "Code": "",
  "Title": "EroticaX - Alexa Grace  Payback is a bitch",
  "Actress": [
    "ALEXA GRACE"
  ],
  "Tag": [
    "lover",
    "swing",
    "seduce",
    "beauty"
  ],
  "Hash": "4fd75ddfed79e05fa33ca8e2901ef8fa",
  "CreatedTime": "2017-10-29 22:54:53",
  "ModifiedTime": "2017-10-29 22:56:12",
  "ViewTime": "01-01-01 00:00:00",
  "FilePath": [
    "K:\\K3\\US+4!X()$EroticaX - Alexa Grace  Payback is a bitch${ALEXA GRACE}[lover,swing,seduce,beauty]=4fd75ddfed79e05fa33ca8e2901ef8fa.mp4"
  ],
  "FileSize": 517318270,
  "Story": "",
  "CountPlay": "0"
}
