{
  "Country": "JP",
  "Rating": 3,
  "Type": "X",
  "Code": "",
  "Title": "Married Woman A",
  "Actress": [],
  "Tag": [
    "cartoon",
    "incest",
    "mother"
  ],
  "Hash": "96060ac8a7f0e2a58adcc3e0e60f5eb9",
  "CreatedTime": "2013-07-28 20:25:13",
  "ModifiedTime": "2013-08-02 11:44:41",
  "ViewTime": "2013-08-02 11:55:03",
  "FilePath": [
    "X:\\X8\\JP+3!X()$Married Woman A${}[cartoon,incest,mother]=96060ac8a7f0e2a58adcc3e0e60f5eb9.avi"
  ],
  "FileSize": 228642816,
  "Story": "",
  "CountPlay": "2"
}
