{
  "Country": "TH",
  "Rating": 2,
  "Type": "X",
  "Code": "",
  "Title": "สาวนมสวย ขึ้นขย่มเอง แบ็คกราวน์ผ้าม่านชมพู",
  "Actress": [],
  "Tag": [
    "clip"
  ],
  "Hash": "9a062c9dbb7e719bf84bec714b5fcadc",
  "CreatedTime": "2013-08-11 23:31:12",
  "ModifiedTime": "2013-08-11 23:31:35",
  "ViewTime": "2013-08-11 23:31:15",
  "FilePath": [
    "X:\\XC\\TH+2!X()$สาวนมสวย ขึ้นขย่มเอง แบ็คกราวน์ผ้าม่านชมพู${}[clip]=9a062c9dbb7e719bf84bec714b5fcadc.3gp"
  ],
  "FileSize": 3447531,
  "Story": "",
  "CountPlay": "1"
}
