{
  "Country": "JP",
  "Rating": 4,
  "Type": "C",
  "Code": "AVOP-276",
  "Title": "Tits Mansion Etc  Lewd Rave Rape Rivalry Bare Tits Battle Each Other Steal Each Other Husband",
  "Actress": [
    "YUMI KAZAMA"
  ],
  "Tag": [
    "lover",
    "mature",
    "swing"
  ],
  "Hash": "c9e0c387c0c1d2eee2841f71de1d0d2c",
  "CreatedTime": "2017-03-30 23:00:35",
  "ModifiedTime": "2021-01-07 18:28:48",
  "ViewTime": "2019-06-19 20:23:34",
  "FilePath": [
    "G:\\4\\JP+4!C(AVOP-276)$Tits Mansion Etc  Lewd Rave Rape Rivalry Bare Tits Battle Each Other Steal Each Other Husband${YUMI KAZAMA}[lover,mature,swing]=c9e0c387c0c1d2eee2841f71de1d0d2c.mp4",
    "G:\\0\\JP+4!C(AVOP-276)$Tits Mansion Etc  Lewd Rave Rape Rivalry Bare Tits Battle Each Other Steal Each Other Husband${YUMI KAZAMA}[lover,mature,swing]=c9e0c387c0c1d2eee2841f71de1d0d2c.mp4",
    "G:\\G7\\__+0!U(AVOP-276)$${YUMI KAZAMA}[]=c9e0c387c0c1d2eee2841f71de1d0d2c.mp4"
  ],
  "FileSize": 4200588252,
  "Story": "",
  "CountPlay": "1"
}
