{
  "Country": "JP",
  "Rating": 4,
  "Type": "C",
  "Code": "LULU-172",
  "Title": "Because I Was Trying To Get Pregnant, My Daughter-in-law Forced Me To Refrain From Masturbation",
  "Actress": [
    "SUMIRE KUROKAWA"
  ],
  "Tag": [
    "cuckold"
  ],
  "Hash": "caa52c9ac163595ad3d91533236c79a9",
  "CreatedTime": "2022-12-06 18:05:01",
  "ModifiedTime": "2025-08-06 01:04:50",
  "ViewTime": "2025-07-19 01:48:26",
  "FilePath": [
    "T:\\4X-600\\JP+4!C(LULU-172)$Because I Was Trying To Get Pregnant, My Daughter-in-law Forced Me To Refrain From Masturbation${SUMIRE KUROKAWA}[cuckold]=caa52c9ac163595ad3d91533236c79a9.mp4"
  ],
  "FileSize": 7213022631,
  "Story": "",
  "CountPlay": "1"
}
