{
  "Country": "JP",
  "Rating": 4,
  "Type": "X",
  "Code": "HEYZO-0454",
  "Title": "Rich Virtual Fuck Heyzo on Redtube",
  "Actress": [
    "SOFIA TAKIGAWA"
  ],
  "Tag": [
    "1080p",
    "big-tit",
    "mature",
    "slut"
  ],
  "Hash": "30373e0e008bcf5c7e2b03f81c9c65c1",
  "CreatedTime": "2015-03-26 10:23:44",
  "ModifiedTime": "2016-02-02 22:17:05",
  "ViewTime": "2016-02-02 22:16:21",
  "FilePath": [
    "Q:\\QI\\JP+4!X(HEYZO-0454)$Rich Virtual Fuck Heyzo on Redtube${SOFIA TAKIGAWA}[1080p,big-tit,mature,slut]=30373e0e008bcf5c7e2b03f81c9c65c1.mp4"
  ],
  "FileSize": 2072636284,
  "Story": "",
  "CountPlay": "2"
}
