{
  "Country": "US",
  "Rating": 2,
  "Type": "X",
  "Code": "",
  "Title": "Taboo American Style 4",
  "Actress": [],
  "Tag": [
    "incest",
    "story"
  ],
  "Hash": "336e2b9f5412d04b1c80d7c15b09cabb",
  "CreatedTime": "2013-07-28 20:14:50",
  "ModifiedTime": "2013-08-02 01:11:38",
  "ViewTime": "2013-08-02 01:10:20",
  "FilePath": [
    "X:\\X8\\US+2!X()$Taboo American Style 4${}[incest,story]=336e2b9f5412d04b1c80d7c15b09cabb.avi"
  ],
  "FileSize": 1149687808,
  "Story": "",
  "CountPlay": "1"
}
