{
  "Country": "JP",
  "Rating": 2,
  "Type": "C",
  "Code": "TGAV-051",
  "Title": "teacher of mini skirt plump thigh erotic provocative too much outrageous cases",
  "Actress": [],
  "Tag": [
    "teacher"
  ],
  "Hash": "3e1d45272d5fe0c2038d2b019f1dee98",
  "CreatedTime": "2015-04-02 00:48:13",
  "ModifiedTime": "2015-04-02 00:52:18",
  "ViewTime": "2015-04-02 00:50:57",
  "FilePath": [
    "Q:\\QV\\JP+2!C(TGAV-051)$teacher of mini skirt plump thigh erotic provocative too much outrageous cases${}[teacher]=3e1d45272d5fe0c2038d2b019f1dee98.avi"
  ],
  "FileSize": 1057962679,
  "Story": "",
  "CountPlay": "1"
}
