{
  "Country": "JP",
  "Rating": 3,
  "Type": "C",
  "Code": "ZEX-363",
  "Title": "Frustrated Wife Stops In Reverse Time All-you-can-eat Cheating With My Husband Colleague",
  "Actress": [
    "SHINODA YUU"
  ],
  "Tag": [
    "1080p",
    "cuckold",
    "pause-time"
  ],
  "Hash": "686e893a25d864ac9b63114c6477a877",
  "CreatedTime": "2019-02-10 22:49:47",
  "ModifiedTime": "2025-08-13 00:07:43",
  "ViewTime": "2025-08-12 23:59:01",
  "FilePath": [],
  "FileSize": 3655365288,
  "Story": "",
  "CountPlay": "1"
}
