{
  "Country": "US",
  "Rating": 5,
  "Type": "X",
  "Code": "",
  "Title": "MRS. DEMEANOR",
  "Actress": [
    "JULIA ANN",
    "ALAYNA DIOR",
    "CARRIE ANN",
    "LISA ANN"
  ],
  "Tag": [
    "720p",
    "incest",
    "mature",
    "mother",
    "big-breast"
  ],
  "Hash": "697c4d8c792e6a6db85d544c2ae705ea",
  "CreatedTime": "2013-08-05 21:40:05",
  "ModifiedTime": "2016-10-31 22:08:47",
  "ViewTime": "2016-10-31 22:36:50",
  "FilePath": [
    "X:\\XA\\US+5!X()$MRS. DEMEANOR${JULIA ANN,ALAYNA DIOR,CARRIE ANN,LISA ANN}[720p,incest,mature,mother,big-breast]=697c4d8c792e6a6db85d544c2ae705ea.mkv"
  ],
  "FileSize": 4698392938,
  "Story": "สาวใหญ่เล่นเด็กหนุ่ม หวานหญ้าอ่อน",
  "CountPlay": "7"
}
