{
  "Country": "__",
  "Rating": 0,
  "Type": "U",
  "Code": "HAVD-888",
  "Title": "havd888",
  "Actress": [],
  "Tag": [],
  "Hash": "1f95dba8a493ccf9d2328aa439f17dd0",
  "CreatedTime": "2015-02-18 22:19:28",
  "ModifiedTime": "2015-03-21 22:13:17",
  "ViewTime": "01-01-01 00:00:00",
  "FilePath": [
    "Q:\\QH\\__+0!U(HAVD-888)$havd888${}[]=1f95dba8a493ccf9d2328aa439f17dd0.mp4",
    "G:\\GXXX\\__+0!U(HAVD-888)$havd888${}[]=1f95dba8a493ccf9d2328aa439f17dd0.mp4"
  ],
  "FileSize": 1093207566,
  "Story": "",
  "CountPlay": "0"
}
