{
  "Country": "JP",
  "Rating": 4,
  "Type": "C",
  "Code": "HAVD-886",
  "Title": "Incest And Adultery With A Slutty Lower Body 3 Pronged Cheating Wives",
  "Actress": [
    "HONJOU YUKA",
    "MATSUMOTO MINAMI",
    "SHIOMI YURIKO"
  ],
  "Tag": [
    "housewife",
    "incest",
    "lover",
    "slut"
  ],
  "Hash": "e23b36d577859696739f25e7b16c5560",
  "CreatedTime": "2015-02-18 22:13:46",
  "ModifiedTime": "2025-08-05 23:47:18",
  "ViewTime": "2016-02-22 20:25:39",
  "FilePath": [
    "T:\\4X-100\\JP+4!C(HAVD-886)$Incest And Adultery With A Slutty Lower Body 3 Pronged Cheating Wives${HONJOU YUKA,MATSUMOTO MINAMI,SHIOMI YURIKO}[housewife,incest,lover,slut]=e23b36d577859696739f25e7b16c5560.mp4",
    "X:\\4X-100\\JP+4!C(HAVD-886)$Incest And Adultery With A Slutty Lower Body 3 Pronged Cheating Wives${HONJOU YUKA,MATSUMOTO MINAMI,SHIOMI YURIKO}[housewife,incest,lover,slut]=e23b36d577859696739f25e7b16c5560.mp4"
  ],
  "FileSize": 1584335622,
  "Story": "",
  "CountPlay": "1"
}
