{
  "Country": "JP",
  "Rating": 3,
  "Type": "C",
  "Code": "",
  "Title": "แอบเห็นพ่อแม่เอากัน แม่มีชู้ พี่ชายเอากับน้อง",
  "Actress": [],
  "Tag": [
    "daughter",
    "incest",
    "lover",
    "mother"
  ],
  "Hash": "e2f89baaa880bc6df357c0c8ed171853",
  "CreatedTime": "2013-07-28 19:57:07",
  "ModifiedTime": "2013-08-03 20:41:18",
  "ViewTime": "2013-08-03 20:40:23",
  "FilePath": [
    "X:\\X8\\JP+3!C()$แอบเห็นพ่อแม่เอากัน แม่มีชู้ พี่ชายเอากับน้อง${}[daughter,incest,lover,mother]=e2f89baaa880bc6df357c0c8ed171853.avi"
  ],
  "FileSize": 943269376,
  "Story": "",
  "CountPlay": "1"
}
