{
  "Country": "JP",
  "Rating": 3,
  "Type": "C",
  "Code": "GAC-002",
  "Title": "Amateur Babe Lost Virgin",
  "Actress": [],
  "Tag": [
    "cute"
  ],
  "Hash": "e55ef7afa2ef077a6144df7c43567d1a",
  "CreatedTime": "2013-06-26 11:23:51",
  "ModifiedTime": "2013-06-26 11:26:06",
  "ViewTime": "2013-06-26 11:24:57",
  "FilePath": [
    "X:\\X4\\JP+3!C(GAC-002)$Amateur Babe Lost Virgin${}[cute]=e55ef7afa2ef077a6144df7c43567d1a.avi"
  ],
  "FileSize": 1668706408,
  "Story": "ไปเปิดซองดาราใหม่\r\nขาวน่ารัก",
  "CountPlay": "1"
}
