{
  "Country": "__",
  "Rating": 0,
  "Type": "U",
  "Code": "",
  "Title": "ก้นงอนขย่มให้ผัวดังต๊าบๆๆ",
  "Actress": [],
  "Tag": [
    "clip"
  ],
  "Hash": "ef8a79057d9f6fa3f911aeaa65fb2ee9",
  "CreatedTime": "2015-01-22 00:35:14",
  "ModifiedTime": "2015-03-21 22:12:54",
  "ViewTime": "01-01-01 00:00:00",
  "FilePath": [
    "Q:\\QG\\__+0!U()$ก้นงอนขย่มให้ผัวดังต๊าบๆๆ${}[clip]=ef8a79057d9f6fa3f911aeaa65fb2ee9.mp4",
    "G:\\GXXX\\__+0!U()$ก้นงอนขย่มให้ผัวดังต๊าบๆๆ${}[clip]=ef8a79057d9f6fa3f911aeaa65fb2ee9.mp4"
  ],
  "FileSize": 17768222,
  "Story": "",
  "CountPlay": "0"
}
