{
  "Country": "US",
  "Rating": 2,
  "Type": "X",
  "Code": "",
  "Title": "Dorcel AirLines",
  "Actress": [],
  "Tag": [
    "air-hostess",
    "cosplay",
    "story"
  ],
  "Hash": "0c80f10541c469bec57223c1fef7ecb1",
  "CreatedTime": "2013-06-18 23:32:52",
  "ModifiedTime": "2013-06-18 23:34:58",
  "ViewTime": "2013-06-18 23:33:41",
  "FilePath": [
    "X:\\X1\\US+2!X()$Dorcel AirLines${}[air-hostess,cosplay,story]=0c80f10541c469bec57223c1fef7ecb1.avi"
  ],
  "FileSize": 731715584,
  "Story": ""
}
