{
  "Country": "JP",
  "Rating": 3,
  "Type": "X",
  "Code": "",
  "Title": "หน้าคล้ายเจนชมพูนุช โดนพามาสอนว่ายน้ำ แทงสด คาชุดว่ายน้ำ",
  "Actress": [],
  "Tag": [
    "swimsuit"
  ],
  "Hash": "da2c472fb9f34e3927e8f4861c2d517b",
  "CreatedTime": "2013-06-23 11:54:47",
  "ModifiedTime": "2013-06-23 11:55:47",
  "ViewTime": "2013-06-23 11:54:49",
  "FilePath": [
    "X:\\X3\\JP+3!X()$หน้าคล้ายเจนชมพูนุช โดนพามาสอนว่ายน้ำ แทงสด คาชุดว่ายน้ำ${}[swimsuit]=da2c472fb9f34e3927e8f4861c2d517b.mpg"
  ],
  "FileSize": 307992092,
  "Story": "",
  "CountPlay": "1"
}
