{
  "Country": "__",
  "Rating": 0,
  "Type": "U",
  "Code": "ONSD-916",
  "Title": "Shake The Hips Rhythm Spans Man Well",
  "Actress": [],
  "Tag": [],
  "Hash": "db1c222a4e6844756a6f9b8ef163cd92",
  "CreatedTime": "2015-04-29 20:29:42",
  "ModifiedTime": "2015-04-29 20:31:44",
  "ViewTime": "01-01-01 00:00:00",
  "FilePath": [
    "G:\\G2\\__+0!U(ONSD-916)$Shake The Hips Rhythm Spans Man Well${}[]=db1c222a4e6844756a6f9b8ef163cd92.mp4"
  ],
  "FileSize": 3000795658,
  "Story": "",
  "CountPlay": "0"
}
