{
  "Country": "US",
  "Rating": 0,
  "Type": "X",
  "Code": "20621",
  "Title": "ApocalX",
  "Actress": [],
  "Tag": [],
  "Hash": "817e89cb5300ffbc83a0f09ef87f0c72",
  "CreatedTime": "2016-07-25 22:41:24",
  "ModifiedTime": "2022-01-14 14:57:25",
  "ViewTime": "01-01-01 00:00:00",
  "FilePath": [
    "T:\\_TORRENT\\US+0!X(20621)$ApocalX${}[]=817e89cb5300ffbc83a0f09ef87f0c72.mp4",
    "G:\\0\\US+0!X(20621)$ApocalX${}[]=817e89cb5300ffbc83a0f09ef87f0c72.mp4",
    "G:\\G1\\US+0!X(20621)$ApocalX${}[]=817e89cb5300ffbc83a0f09ef87f0c72.mp4"
  ],
  "FileSize": 2317384840,
  "Story": "",
  "CountPlay": "0"
}
