{
  "Country": "TH",
  "Rating": 4,
  "Type": "X",
  "Code": "",
  "Title": "¶Å¡¼éÒ¶Ø§«ÍÂ áµ¡ã¹",
  "Actress": [],
  "Tag": [
    "clip",
    "mature"
  ],
  "Hash": "83771034149d8cb6e888aa7c153a8dee",
  "CreatedTime": "2014-02-22 01:31:33",
  "ModifiedTime": "2025-08-05 23:48:02",
  "ViewTime": "2016-10-20 23:10:18",
  "FilePath": [
    "T:\\4X-400\\TH+4!X()$¶Å¡¼éÒ¶Ø§«ÍÂ áµ¡ã¹${}[clip,mature]=83771034149d8cb6e888aa7c153a8dee.mp4",
    "X:\\4X-400\\TH+4!X()$¶Å¡¼éÒ¶Ø§«ÍÂ áµ¡ã¹${}[clip,mature]=83771034149d8cb6e888aa7c153a8dee.mp4"
  ],
  "FileSize": 51384842,
  "Story": "",
  "CountPlay": "6"
}
