{
  "Country": "JP",
  "Rating": 3,
  "Type": "X",
  "Code": "OPB-009",
  "Title": "Please eat me Sally",
  "Actress": [
    "SALLY YOSHINO"
  ],
  "Tag": [
    "cosplay"
  ],
  "Hash": "87a101a7f0d04afc663dd4de05ac54c5",
  "CreatedTime": "2016-02-25 20:47:19",
  "ModifiedTime": "2016-03-16 22:35:48",
  "ViewTime": "2016-03-16 22:34:58",
  "FilePath": [
    "G:\\G5\\JP+3!X(OPB-009)$Please eat me Sally${SALLY YOSHINO}[cosplay]=87a101a7f0d04afc663dd4de05ac54c5.avi"
  ],
  "FileSize": 733000612,
  "Story": "",
  "CountPlay": "1"
}
