{
  "Country": "JP",
  "Rating": 5,
  "Type": "C",
  "Code": "SNIS-280",
  "Title": "Mixed Body Fluids, Deep Sex",
  "Actress": [],
  "Tag": [
    "cosplay",
    "kiss",
    "slut",
    "bathroom",
    "car",
    "outdoor"
  ],
  "Hash": "8a7485abc7e5747f379db3e059832b34",
  "CreatedTime": "2015-02-18 23:00:38",
  "ModifiedTime": "2019-05-20 21:26:17",
  "ViewTime": "2016-02-24 00:28:04",
  "FilePath": [
    "G:\\GXXX\\__+0!U(SNIS-280)$SNIS-280${}[]=8a7485abc7e5747f379db3e059832b34.mp4"
  ],
  "FileSize": 1452599986,
  "Story": "",
  "CountPlay": "2"
}
