{
  "Country": "__",
  "Rating": 0,
  "Type": "U",
  "Code": "MGDN-143",
  "Title": "",
  "Actress": [],
  "Tag": [],
  "Hash": "8fdd46cdfa6c3bf6f9d95101bbd2a458",
  "CreatedTime": "2021-01-06 16:32:47",
  "ModifiedTime": "2021-01-07 18:29:17",
  "ViewTime": "01-01-01 00:00:00",
  "FilePath": [
    "G:\\0\\__+0!U(MGDN-143)$${}[]=8fdd46cdfa6c3bf6f9d95101bbd2a458.mp4",
    "G:\\\\__+0!U(MGDN-143)$${}[]=8fdd46cdfa6c3bf6f9d95101bbd2a458.mp4"
  ],
  "FileSize": 3992991267,
  "Story": "",
  "CountPlay": "0"
}
