{
  "Country": "US",
  "Rating": 0,
  "Type": "X",
  "Code": "",
  "Title": "Xena Warrior Princess XXX jiggly-xena-cd1",
  "Actress": [],
  "Tag": [
    "parody"
  ],
  "Hash": "5cbd7982e6499f98737ec2c0bf8bc922",
  "CreatedTime": "2015-02-18 22:34:17",
  "ModifiedTime": "2015-03-21 22:13:33",
  "ViewTime": "01-01-01 00:00:00",
  "FilePath": [
    "Q:\\QI\\US+0!X()$Xena Warrior Princess XXX jiggly-xena-cd1${}[parody]=5cbd7982e6499f98737ec2c0bf8bc922.avi",
    "G:\\GXXX\\US+0!X()$Xena Warrior Princess XXX jiggly-xena-cd1${}[parody]=5cbd7982e6499f98737ec2c0bf8bc922.avi"
  ],
  "FileSize": 734697472,
  "Story": "",
  "CountPlay": "0"
}
