{
  "Country": "US",
  "Rating": 3,
  "Type": "X",
  "Code": "",
  "Title": "Wolfmen 3D",
  "Actress": [],
  "Tag": [
    "animation",
    "cartoon",
    "gangbang",
    "rape"
  ],
  "Hash": "5f0c882f653a5b6987d25ad68dafe6ed",
  "CreatedTime": "2013-06-19 14:29:29",
  "ModifiedTime": "2013-06-19 14:30:43",
  "ViewTime": "2013-06-19 14:29:34",
  "FilePath": [
    "X:\\X1\\US+3!X()$Wolfmen 3D${}[animation,cartoon,gangbang,rape]=5f0c882f653a5b6987d25ad68dafe6ed.mpg"
  ],
  "FileSize": 531839735,
  "Story": ""
}
