{
  "Country": "JP",
  "Rating": 4,
  "Type": "X",
  "Code": "HEYZO-0302",
  "Title": "First back",
  "Actress": [
    "SUKURA AIDA"
  ],
  "Tag": [
    "1080p",
    "cute",
    "swing"
  ],
  "Hash": "5f4895a3a42589f4ff2de7028c8f92ee",
  "CreatedTime": "2014-03-22 06:03:08",
  "ModifiedTime": "2022-01-13 18:42:05",
  "ViewTime": "2016-03-30 00:43:42",
  "FilePath": [
    "T:\\4X-400\\JP+4!X(HEYZO-0302)$First back${SUKURA AIDA}[1080p,cute,swing]=5f4895a3a42589f4ff2de7028c8f92ee.mp4",
    "X:\\4X-400\\JP+4!X(HEYZO-0302)$First back${SUKURA AIDA}[1080p,cute,swing]=5f4895a3a42589f4ff2de7028c8f92ee.mp4"
  ],
  "FileSize": 2266059051,
  "Story": "",
  "CountPlay": "3"
}
